EELSFitter/__init__.py
EELSFitter/version.py
EELSFitter/core/__init__.py
EELSFitter/core/gainpeakfitter.py
EELSFitter/core/spectral_image.py
EELSFitter/core/training.py
EELSFitter/plotting/__init__.py
EELSFitter/plotting/heatmaps.py
EELSFitter/plotting/hyperparameters.py
EELSFitter/plotting/mva_perf.py
EELSFitter/plotting/training_perf.py
EELSFitter/plotting/zlp.py
EELSFitter-3.1.0.dist-info/LICENSE
EELSFitter-3.1.0.dist-info/METADATA
EELSFitter-3.1.0.dist-info/WHEEL
EELSFitter-3.1.0.dist-info/top_level.txt
EELSFitter-3.1.0.dist-info/RECORD
