Metadata-Version: 2.1
Name: EELSFitter
Version: 3.1.0
Summary: Electron Energy Loss Spectroscopy Fitter
Home-page: https://github.com/LHCfitNikhef/EELSfitter
Author: J.M. Sangers, A. Brokkelkamp, J.J. ter Hoeve, I. Postmes, L. Maduro, J. Rojo, S. Conesa Boj
Author-email: j.j.ter.hoeve@vu.nl
Project-URL: Documentation, https://lhcfitnikhef.github.io/EELSfitter
Classifier: Operating System :: Unix
Classifier: Programming Language :: Python :: 3
Classifier: Topic :: Scientific/Engineering :: Physics
Classifier: License :: OSI Approved :: GNU General Public License v3 (GPLv3)
Requires-Python: >=3.7
License-File: LICENSE
Requires-Dist: ncempy>=1.8.0
Requires-Dist: matplotlib>=3.3.2
Requires-Dist: numpy>=1.19.2
Requires-Dist: natsort>=7.1.0
Requires-Dist: scipy>=1.5.2
Requires-Dist: torch>=1.6.0
Requires-Dist: scikit-learn>=1.0
Requires-Dist: kneed>=0.8
